django_testbox-0.0.2.dist-info/DESCRIPTION.rst
django_testbox-0.0.2.dist-info/METADATA
django_testbox-0.0.2.dist-info/RECORD
django_testbox-0.0.2.dist-info/WHEEL
django_testbox-0.0.2.dist-info/metadata.json
django_testbox-0.0.2.dist-info/top_level.txt
testbox/__init__.py
testbox/helpers.py
testbox/mixins.py
testbox/testcase.py
