Metadata-Version: 2.0
Name: django-testbox
Version: 0.0.2
Summary: Testing tools for Django projects
Home-page: https://github.com/mtirsel/django-testbox
Author: Martin Tiršel
Author-email: martin.tirsel@gmail.com
License: UNKNOWN
Keywords: django testing development
Platform: UNKNOWN
Classifier: Development Status :: 3 - Alpha
Classifier: Intended Audience :: Developers
Classifier: Topic :: Software Development :: Testing
Classifier: Programming Language :: Python :: 3.4
Requires-Dist: django
Requires-Dist: selenium
